napari_accelerated_pixel_and_object_classification/__init__.py
napari_accelerated_pixel_and_object_classification/_custom_table_row_classifier.py
napari_accelerated_pixel_and_object_classification/_dock_widget.py
napari_accelerated_pixel_and_object_classification/_function.py
napari_accelerated_pixel_and_object_classification/_object_classification_widget.py
napari_accelerated_pixel_and_object_classification/_object_merger.py
napari_accelerated_pixel_and_object_classification/_surface_vertex_classifier.py
napari_accelerated_pixel_and_object_classification/_utilities.py
napari_accelerated_pixel_and_object_classification/_tests/__init__.py
napari_accelerated_pixel_and_object_classification/_tests/test_functions.py
napari_accelerated_pixel_and_object_classification/_tests/test_widgets.py
napari_accelerated_pixel_and_object_classification-0.14.1.dist-info/LICENSE
napari_accelerated_pixel_and_object_classification-0.14.1.dist-info/METADATA
napari_accelerated_pixel_and_object_classification-0.14.1.dist-info/WHEEL
napari_accelerated_pixel_and_object_classification-0.14.1.dist-info/entry_points.txt
napari_accelerated_pixel_and_object_classification-0.14.1.dist-info/top_level.txt
napari_accelerated_pixel_and_object_classification-0.14.1.dist-info/RECORD
