Metadata-Version: 2.1
Name: napari-accelerated-pixel-and-object-classification
Version: 0.14.1
Summary: Pixel and label classification using OpenCL-based Random Forest Classifiers
Home-page: https://github.com/haesleinhuepf/napari-accelerated-pixel-and-object-classification
Author: Robert Haase
Author-email: robert.haase@tu-dresden.de
License: BSD-3
Project-URL: Bug Tracker, https://github.com/haesleinhuepf/napari-accelerated-pixel-and-object-classification/issues
Project-URL: Documentation, https://github.com/haesleinhuepf/napari-accelerated-pixel-and-object-classification
Project-URL: Source Code, https://github.com/haesleinhuepf/napari-accelerated-pixel-and-object-classification
Project-URL: User Support, https://forum.image.sc/tag/clij
Classifier: Development Status :: 3 - Alpha
Classifier: Intended Audience :: Science/Research
Classifier: Framework :: napari
Classifier: Topic :: Scientific/Engineering :: Image Processing
Classifier: Topic :: Scientific/Engineering :: Information Analysis
Classifier: Programming Language :: Python
Classifier: Programming Language :: Python :: 3
Classifier: Programming Language :: Python :: 3.7
Classifier: Programming Language :: Python :: 3.8
Classifier: Programming Language :: Python :: 3.9
Classifier: Operating System :: OS Independent
Classifier: License :: OSI Approved :: BSD License
Requires-Python: >=3.7
License-File: LICENSE
Requires-Dist: napari-plugin-engine >=0.1.4
Requires-Dist: numpy
Requires-Dist: apoc >=0.12.0
Requires-Dist: napari-tools-menu >=0.1.17
Requires-Dist: napari-time-slicer
Requires-Dist: superqt
Requires-Dist: imageio !=2.22.1
Requires-Dist: napari >=0.4.11
Requires-Dist: napari-assistant >=0.4.7
